uyghur_ocr/__init__.py
uyghur_ocr/py.typed
uyghur_ocr-0.0.0.dist-info/METADATA
uyghur_ocr-0.0.0.dist-info/WHEEL
uyghur_ocr-0.0.0.dist-info/licenses/LICENSE
uyghur_ocr-0.0.0.dist-info/RECORD
